refactor/__init__.py
refactor/__main__.py
refactor/actions.py
refactor/ast.py
refactor/change.py
refactor/common.py
refactor/context.py
refactor/core.py
refactor/runner.py
refactor/validate_inputs.py
refactor/internal/__init__.py
refactor/internal/action_optimizer.py
refactor/internal/ast_delta.py
refactor/internal/graph_access.py
refactor/internal/position_provider.py
refactor-0.6.3.dist-info/LICENSE.txt
refactor-0.6.3.dist-info/METADATA
refactor-0.6.3.dist-info/WHEEL
refactor-0.6.3.dist-info/entry_points.txt
refactor-0.6.3.dist-info/top_level.txt
refactor-0.6.3.dist-info/RECORD
