Metadata-Version: 2.1
Name: refactor
Version: 0.6.3
Summary: AST-based fragmental source code refactoring toolkit
Home-page: https://github.com/isidentical/refactor
Author: isidentical
Author-email: isidentical@gmail.com
License: MIT
Project-URL: Documentation, https://refactor.readthedocs.io/
Project-URL: Source, https://github.com/isidentical/refactor
Project-URL: Tracker, https://github.com/isidentical/refactor/issues
Classifier: License :: OSI Approved :: MIT License
Classifier: Programming Language :: Python :: 3
Classifier: Programming Language :: Python :: 3 :: Only
Classifier: Programming Language :: Python :: 3.9
Classifier: Programming Language :: Python :: 3.10
Classifier: Programming Language :: Python :: 3.11
Requires-Python: >=3.9
License-File: LICENSE.txt
